multidiff/__init__.py
multidiff/diff_non_linear.py
multidiff/diffusion_matrix.py
multidiff/io.py
multidiff/synthetic.py
multidiff-0.2.1.dist-info/LICENSE
multidiff-0.2.1.dist-info/METADATA
multidiff-0.2.1.dist-info/WHEEL
multidiff-0.2.1.dist-info/top_level.txt
multidiff-0.2.1.dist-info/RECORD
