Metadata-Version: 2.1
Name: multidiff
Version: 0.2.1
Summary: A fitting package for the analysis of multicomponent diffusion data
Home-page: https://github.com/chemical-diffusion/multi-diffusion
Author: Emmanuelle Gouillart
Author-email: emmanuelle.gouillart@gmail.com
License: UNKNOWN
Platform: UNKNOWN
Requires-Dist: matplotlib
Requires-Dist: numpy
Requires-Dist: scipy
